pyPackage/__init__.py
pyPackage/__main__.py
pyPackage/options.py
pyPackage/package.py
pyInstallPackage-0.3.dist-info/LICENSE
pyInstallPackage-0.3.dist-info/METADATA
pyInstallPackage-0.3.dist-info/WHEEL
pyInstallPackage-0.3.dist-info/top_level.txt
pyInstallPackage-0.3.dist-info/RECORD
