Metadata-Version: 2.1
Name: pyInstallPackage
Version: 0.3
Summary: Standard app packaging
Home-page: https://github.com/20centcroak/pyPackage
Author: 20centCroak
Author-email: 
License: UNKNOWN
Platform: UNKNOWN
Classifier: Programming Language :: Python :: 3
Classifier: License :: OSI Approved :: MIT License
Classifier: Operating System :: OS Independent
Requires-Python: >=3.6
License-File: LICENSE
Requires-Dist: PyBaseApp
Requires-Dist: PyInstaller
